elevator_control.v
module elevator_control(
    input clk,
    input reset,
    input [3:0] up_req, down_req,
    output reg [1:0] current_floor,
    output reg moving_up, moving_down, door_open
);

    
    parameter IDLE = 2'd0;
    parameter MOVING_UP = 2'd1;
    parameter MOVING_DOWN = 2'd2;
    parameter DOOR_OPEN = 2'd3;

    reg [1:0] state, next_state;
    reg [3:0] requests;
    reg [1:0] target_floor;

    integer i;


    always @(posedge clk or posedge reset) begin
        if (reset)
            requests <= 4'b0000;
        else
            requests <= requests | up_req | down_req;
    end

    
    always @(posedge clk or posedge reset) begin
        if (reset)
            state <= IDLE;
        else
            state <= next_state;
    end

   
    always @(posedge clk or posedge reset) begin
        if (reset)
            current_floor <= 0;
        else begin
            if (state == MOVING_UP && current_floor < target_floor)
                current_floor <= current_floor + 1;
            else if (state == MOVING_DOWN && current_floor > target_floor)
                current_floor <= current_floor - 1;
            else if (state == DOOR_OPEN)
                requests[current_floor] <= 0; 
        end
    end

    
    task find_next_up;
        input [3:0] reqs;
        input [1:0] floor;
        output [1:0] next_floor;
        begin
            next_floor = floor;
            for (i = floor+1; i < 4; i = i + 1)
                if (reqs[i])
                    next_floor = i[1:0];
        end
    endtask

    task find_next_down;
        input [3:0] reqs;
        input [1:0] floor;
        output [1:0] next_floor;
        begin
            next_floor = floor;
            for (i = floor-1; i >= 0; i = i - 1)
                if (reqs[i])
                    next_floor = i[1:0];
        end
    endtask

    // FSM logic
    always @(*) begin
        next_state = state;
        moving_up = 0;
        moving_down = 0;
        door_open = 0;

        case (state)
            IDLE: begin
                if (|requests) begin
                    if (requests > (1 << current_floor)) begin
                        next_state = MOVING_UP;
                        find_next_up(requests, current_floor, target_floor);
                    end else if (requests < (1 << current_floor)) begin
                        next_state = MOVING_DOWN;
                        find_next_down(requests, current_floor, target_floor);
                    end else
                        next_state = DOOR_OPEN;
                end
            end

            MOVING_UP: begin
                moving_up = 1;
                if (current_floor == target_floor)
                    next_state = DOOR_OPEN;
            end

            MOVING_DOWN: begin
                moving_down = 1;
                if (current_floor == target_floor)
                    next_state = DOOR_OPEN;
            end

            DOOR_OPEN: begin
                door_open = 1;
                next_state = IDLE;
            end
        endcase
    end
endmodule

tb_elevator.v
module tb_elevator;
    reg clk, reset;
    reg [3:0] up_req, down_req;
    wire [1:0] current_floor;
    wire moving_up, moving_down, door_open;

    // Instantiate the elevator module
    elevator_control uut(
        .clk(clk),
        .reset(reset),
        .up_req(up_req),
        .down_req(down_req),
        .current_floor(current_floor),
        .moving_up(moving_up),
        .moving_down(moving_down),
        .door_open(door_open)
    );

    // Clock generation
    initial clk = 0;
    always #5 clk = ~clk;

    // Simulation stimulus
    initial begin
        $dumpfile("elevator.vcd");
        $dumpvars(0, tb_elevator);

        reset = 1; up_req = 0; down_req = 0;
        #10 reset = 0;

        #10 up_req = 4'b0101;   
        #20 up_req = 4'b0000;
        #50 down_req = 4'b1000; 
        #40 down_req = 4'b0000;
        #30 up_req = 4'b0010;   
        #20 up_req = 4'b0000;

        #25 down_req = 4'b0100; 
        #30 down_req = 4'b0000;

        #40 up_req = 4'b1001;   
        #20 up_req = 4'b0000;

        #600 $finish;           
    end

    
    always @(posedge clk) begin
        $display("Time: %0d | Floor: %0d | Up: %b | Down: %b | Door: %b | Requests: %b",
                 $time, current_floor, moving_up, moving_down, door_open, uut.requests);
    end

endmodule

elevator.vcd
$date
	Wed Oct 08 12:42:04 2025
$end
$version
	Icarus Verilog
$end
$timescale
	1s
$end
$scope module tb_elevator $end
$var wire 1 ! moving_up $end
$var wire 1 " moving_down $end
$var wire 1 # door_open $end
$var wire 2 $ current_floor [1:0] $end
$var reg 1 % clk $end
$var reg 4 & down_req [3:0] $end
$var reg 1 ' reset $end
$var reg 4 ( up_req [3:0] $end
$scope module uut $end
$var wire 1 % clk $end
$var wire 4 ) down_req [3:0] $end
$var wire 1 ' reset $end
$var wire 4 * up_req [3:0] $end
$var reg 2 + current_floor [1:0] $end
$var reg 1 # door_open $end
$var reg 1 " moving_down $end
$var reg 1 ! moving_up $end
$var reg 2 , next_state [1:0] $end
$var reg 4 - requests [3:0] $end
$var reg 2 . state [1:0] $end
$var reg 2 / target_floor [1:0] $end
$var integer 32 0 i [31:0] $end
$scope task find_next_down $end
$var reg 2 1 floor [1:0] $end
$var reg 2 2 next_floor [1:0] $end
$var reg 4 3 reqs [3:0] $end
$upscope $end
$scope task find_next_up $end
$var reg 2 4 floor [1:0] $end
$var reg 2 5 next_floor [1:0] $end
$var reg 4 6 reqs [3:0] $end
$upscope $end
$upscope $end
$upscope $end
$enddefinitions $end
#0
$dumpvars
bx 6
bx 5
bx 4
bx 3
bx 2
bx 1
bx 0
bx /
b0 .
b0 -
b0 ,
b0 +
b0 *
b0 )
b0 (
1'
b0 &
0%
b0 $
0#
0"
0!
$end
#5
1%
#10
0%
0'
#15
1%
#20
0%
b101 (
b101 *
#25
b10 /
b100 0
b10 5
b0 4
b101 6
b1 ,
b101 -
1%
#30
0%
#35
1!
b1 .
1%
#40
0%
b0 (
b0 *
#45
1!
b1 $
b1 +
1%
#50
0%
#55
b11 ,
1!
b10 $
b10 +
1%
#60
0%
#65
b0 ,
1#
0!
b11 .
1%
#70
0%
#75
b100 0
b10 4
b1 ,
0#
b0 .
b101 -
1%
#80
0%
#85
b11 ,
1!
b1 .
1%
#90
0%
b1000 &
b1000 )
#95
b0 ,
1#
0!
b1101 -
b11 .
1%
#100
0%
#105
b11 /
b11 5
b100 0
b1001 6
b1 ,
0#
b1001 -
b0 .
1%
#110
0%
#115
1!
b1 .
1%
#120
0%
#125
b11 ,
1!
b11 $
b11 +
1%
#130
0%
b0 &
b0 )
#135
b0 ,
1#
0!
b11 .
1%
#140
0%
#145
b0 /
b11111111111111111111111111111111 0
b0 2
b11 1
b1 3
b10 ,
0#
b1 -
b0 .
1%
#150
0%
#155
1"
b10 .
1%
#160
0%
b10 (
b10 *
#165
1"
b10 $
b10 +
b11 -
1%
#170
0%
#175
1"
b1 $
b1 +
1%
#180
0%
b0 (
b0 *
#185
b11 ,
1"
b0 $
b0 +
1%
#190
0%
#195
b0 ,
1#
0"
b11 .
1%
#200
0%
#205
b10 /
b100 0
b10 5
b0 4
b110 6
b1 ,
0#
b0 .
b110 -
1%
b100 &
b100 )
#210
0%
#215
1!
b1 .
1%
#220
0%
#225
1!
b1 $
b1 +
1%
#230
0%
#235
b11 ,
1!
b10 $
b10 +
1%
b0 &
b0 )
#240
0%
#245
b0 ,
1#
0!
b11 .
1%
#250
0%
#255
b100 0
b10 4
b1 ,
0#
b0 .
b110 -
1%
#260
0%
#265
b11 ,
1!
b1 .
1%
#270
0%
#275
b0 ,
1#
0!
b1111 -
b11 .
1%
b1001 (
b1001 *
#280
0%
#285
b11 /
b11 5
b100 0
b1011 6
b1 ,
0#
b1011 -
b0 .
1%
#290
0%
#295
1!
b1 .
1%
b0 (
b0 *
#300
0%
#305
b11 ,
1!
b11 $
b11 +
1%
#310
0%
#315
b0 ,
1#
0!
b11 .
1%
#320
0%
#325
b0 /
b11111111111111111111111111111111 0
b0 2
b11 3
b10 ,
0#
b11 -
b0 .
1%
#330
0%
#335
1"
b10 .
1%
#340
0%
#345
1"
b10 $
b10 +
1%
#350
0%
#355
1"
b1 $
b1 +
1%
#360
0%
#365
b11 ,
1"
b0 $
b0 +
1%
#370
0%
#375
b0 ,
1#
0"
b11 .
1%
#380
0%
#385
b1 /
b100 0
b1 5
b0 4
b10 6
b1 ,
0#
b10 -
b0 .
1%
#390
0%
#395
1!
b1 .
1%
#400
0%
#405
b11 ,
1!
b1 $
b1 +
1%
#410
0%
#415
b0 ,
1#
0!
b11 .
1%
#420
0%
#425
0#
b0 -
b0 .
1%
